sbppypitestapp/__init__.py
sbppypitestapp/__main__.py
sbppypitestapp/py.typed
sbppypitestapp/sbppypitestapp.py
sbppypitestapp-0.1.2.dist-info/WHEEL
sbppypitestapp-0.1.2.dist-info/entry_points.txt
sbppypitestapp-0.1.2.dist-info/METADATA
sbppypitestapp-0.1.2.dist-info/RECORD
