Metadata-Version: 2.3
Name: sbppypitestapp
Version: 0.1.2
Summary: Development flow as Paleofuturistic Python
Author: Paleofuturistic Python
Author-email: Paleofuturistic Python <me@here.now>
Classifier: License :: OSI Approved :: Apache Software License
Classifier: Programming Language :: Python :: 3.12
Requires-Dist: sbppypitestlib>=0.1.0
Requires-Python: >=3.12
